kingcow/__init__.py
kingcow/api.py
kingcow/html_handle.py
kingcow/request.py
kingcow/spider.py
kingcow/xml_handle.py
kingcow-1.0.1.dist-info/LICENSE
kingcow-1.0.1.dist-info/METADATA
kingcow-1.0.1.dist-info/WHEEL
kingcow-1.0.1.dist-info/top_level.txt
kingcow-1.0.1.dist-info/RECORD
