Metadata-Version: 2.1
Name: kingcow
Version: 1.0.1
Summary: This is a library for web page parsing and web page requests
Home-page: https://github.com/Zhou-chengy/kingcow/
Author: Zhou_Chengyu
Author-email: earuil@outlook.com
License: UNKNOWN
Platform: UNKNOWN
